<?xml version="1.0" encoding="UTF-8"?>
<con:soapui-project id="89c4b0f2-a353-4905-afa9-0af0e060e263" activeEnvironment="Default" name="REST Project 1" soapui-version="5.3.0" xmlns:con="http://eviware.com/soapui/config"><con:settings/><con:interface xsi:type="con:RestService" id="e9d388a7-be34-4580-8718-96da31629137" wadlVersion="http://wadl.dev.java.net/2009/02" name="http://localhost:8080" type="rest" xmlns:xsi="http://www.w3.org/2001/XMLSchema-instance"><con:settings/><con:definitionCache/><con:endpoints><con:endpoint>http://localhost:8080</con:endpoint></con:endpoints><con:resource name="Vote-for-lunch" path="/vote-for-lunch/rest/admin/users/" id="53e5c09f-00a2-44ac-a9a7-b47445d118a9"><con:settings/><con:parameters/><con:method name="get users" id="65c14d42-7957-485c-bcab-7ffcd62fbcbb" method="GET"><con:settings/><con:parameters/><con:representation type="RESPONSE"><con:mediaType>application/json;charset=UTF-8</con:mediaType><con:status>200</con:status><con:params/><con:element>Response</con:element></con:representation><con:representation type="FAULT"><con:mediaType>text/html;charset=utf-8</con:mediaType><con:status>500</con:status><con:params/><con:element>html</con:element></con:representation><con:request name="Request 1" id="232f8f32-c1bb-4cc1-a7d2-fdd9a867e2bc" mediaType="application/json" postQueryString="false"><con:settings><con:setting id="com.eviware.soapui.impl.wsdl.WsdlRequest@request-headers">&lt;xml-fragment/></con:setting></con:settings><con:endpoint>http://localhost:8080</con:endpoint><con:request/><con:originalUri>http://localhost/vote-for-lunch/rest/users</con:originalUri><con:credentials><con:authType>No Authorization</con:authType></con:credentials><con:jmsConfig JMSDeliveryMode="PERSISTENT"/><con:jmsPropertyConfig/><con:parameters/><con:parameterOrder/></con:request></con:method><con:method name="New user" id="f1c23110-38a4-4593-99da-c7be1b5f606d" method="POST"><con:settings/><con:parameters/><con:representation type="RESPONSE"><con:mediaType>application/json;charset=UTF-8</con:mediaType><con:status>201</con:status><con:params/><con:element xmlns:user="http://localhost/vote-for-lunch/rest/users">user:Response</con:element></con:representation><con:representation type="REQUEST"><con:mediaType>application/json</con:mediaType><con:params/></con:representation><con:request name="Request 1" id="db88a979-03b0-475b-95ca-e809ef3f7ba9" mediaType="application/json" postQueryString="false"><con:settings><con:setting id="com.eviware.soapui.impl.wsdl.WsdlRequest@request-headers">&lt;xml-fragment/></con:setting></con:settings><con:endpoint>http://localhost:8080</con:endpoint><con:request>{
      "name": "User2",
      "email": "user2@yandex.ru",
      "password": "password",
      "enabled": true,
      "roles": ["ROLE_USER"]
   }</con:request><con:originalUri>http://localhost/vote-for-lunch/rest/users</con:originalUri><con:credentials><con:authType>No Authorization</con:authType></con:credentials><con:jmsConfig JMSDeliveryMode="PERSISTENT"/><con:jmsPropertyConfig/><con:parameters/><con:parameterOrder/></con:request></con:method><con:method name="UpdateUser" id="f863d247-24c4-4b4d-8982-ba5ab5c27e88" method="PUT"><con:settings/><con:parameters/><con:representation type="REQUEST"><con:mediaType>application/json</con:mediaType><con:params/></con:representation><con:representation type="FAULT"><con:mediaType>text/html;charset=utf-8</con:mediaType><con:status>500 405</con:status><con:params/><con:element>html</con:element></con:representation><con:representation type="RESPONSE"><con:mediaType xsi:nil="true"/><con:status>200</con:status><con:params/><con:element>data</con:element></con:representation><con:representation type="RESPONSE"><con:mediaType xsi:nil="true"/><con:status>200</con:status><con:params/><con:element>data</con:element></con:representation><con:representation type="RESPONSE"><con:mediaType xsi:nil="true"/><con:status>200</con:status><con:params/><con:element>data</con:element></con:representation><con:representation type="RESPONSE"><con:mediaType xsi:nil="true"/><con:status>200</con:status><con:params/><con:element>data</con:element></con:representation><con:request name="Request 1" id="20ff1085-a3b2-42a0-af4d-326569510ba5" mediaType="application/json" postQueryString="false"><con:settings><con:setting id="com.eviware.soapui.impl.wsdl.WsdlRequest@request-headers">&lt;xml-fragment/></con:setting></con:settings><con:endpoint>http://localhost:8080</con:endpoint><con:request>{
      "id": 100013,
      "name": "Upd User",
      "email": "user2@yandex.ru",
      "password": "password",
      "enabled": true,
      "roles": ["ROLE_USER"]
   }</con:request><con:originalUri>http://localhost/vote-for-lunch/rest/users</con:originalUri><con:credentials><con:authType>No Authorization</con:authType></con:credentials><con:jmsConfig JMSDeliveryMode="PERSISTENT"/><con:jmsPropertyConfig/><con:parameters/><con:parameterOrder/></con:request></con:method><con:method name="Delete user" id="6a4a5ac9-4e91-4d42-a8eb-ecae242f0499" method="DELETE"><con:settings/><con:parameters/><con:representation type="RESPONSE"><con:mediaType xsi:nil="true"/><con:status>200</con:status><con:params/><con:element>data</con:element></con:representation><con:representation type="REQUEST"><con:mediaType>application/json</con:mediaType><con:params/></con:representation><con:representation type="FAULT"><con:mediaType>text/html;charset=utf-8</con:mediaType><con:status>500</con:status><con:params/><con:element>html</con:element></con:representation><con:request name="Request 1" id="aa1f1f48-162a-48c5-940f-a42ea0b24b6e" mediaType="application/json" postQueryString="false"><con:settings><con:setting id="com.eviware.soapui.impl.wsdl.WsdlRequest@request-headers">&lt;xml-fragment/></con:setting></con:settings><con:endpoint>http://localhost:8080</con:endpoint><con:request/><con:originalUri>http://localhost/vote-for-lunch/rest/users</con:originalUri><con:credentials><con:authType>No Authorization</con:authType></con:credentials><con:jmsConfig JMSDeliveryMode="PERSISTENT"/><con:jmsPropertyConfig/><con:parameters/><con:parameterOrder/></con:request></con:method></con:resource></con:interface><con:properties/><con:wssContainer/><con:oAuth2ProfileContainer/><con:oAuth1ProfileContainer/></con:soapui-project>